dailypublisherrevenue/__init__.py
dailypublisherrevenue/dailyrevenue.py
thelatesttest-1.0.dist-info/METADATA
thelatesttest-1.0.dist-info/WHEEL
thelatesttest-1.0.dist-info/top_level.txt
thelatesttest-1.0.dist-info/RECORD
